conapp/__init__.py
conapp/__main__.py
conapp/arguments.py
conapp/definitions.py
conapp/file_ops.py
conapp/file_paths.py
conapp/url_generators.py
conapp/validate.py
conapp/commands/__init__.py
conapp/commands/apply.py
conapp/commands/config.py
conapp/commands/local.py
conapp/commands/snapshots.py
conapp-1.0.0.dist-info/LICENSE
conapp-1.0.0.dist-info/METADATA
conapp-1.0.0.dist-info/WHEEL
conapp-1.0.0.dist-info/entry_points.txt
conapp-1.0.0.dist-info/top_level.txt
conapp-1.0.0.dist-info/RECORD
