Metadata-Version: 2.1
Name: conapp
Version: 1.0.0
Summary: A simple config applier
Home-page: https://bitbucket.org/drew887/conapp/src/master/
Author: drew887 <Andrew Mcdonald>
Author-email: drew887121@gmail.com
License: UNKNOWN
Platform: UNKNOWN
Classifier: Programming Language :: Python :: 3
Classifier: License :: OSI Approved :: MIT License
Classifier: Operating System :: OS Independent
Requires-Python: >=3.6
